czthry/__init__.py
czthry/alog.py
czthry/async_call.py
czthry/async_jobs.py
czthry/concurrent_jobs.py
czthry/dbmanager.py
czthry/encrypt.py
czthry/env.py
czthry/func_time.py
czthry/jsobj.py
czthry/method_register.py
czthry/myconcurrent.py
czthry/myredis.py
czthry/mythread.py
czthry/progress_bar.py
czthry/proxy.py
czthry/terminal_color.py
czthry/useragent.py
czthry/util.py
czthry-0.1.2.dist-info/LICENSE
czthry-0.1.2.dist-info/METADATA
czthry-0.1.2.dist-info/WHEEL
czthry-0.1.2.dist-info/top_level.txt
czthry-0.1.2.dist-info/RECORD
