Metadata-Version: 2.1
Name: czthry
Version: 0.1.2
Summary: A small example package
Author-email: thr <22227124@qq.com>
License: Copyright (c) 2018 The Python Packaging Authority
Project-URL: Homepage, https://github.com/Taohr
Project-URL: Bug Tracker, https://github.com/Taohr/private/tree/mypypi
Classifier: Programming Language :: Python :: 3
Classifier: License :: OSI Approved :: MIT License
Classifier: Operating System :: OS Independent
Requires-Python: >=3.6
License-File: LICENSE
Requires-Dist: progressbar ==2.5
Requires-Dist: redis ==4.3.4
Requires-Dist: SQLAlchemy ==1.4.39
Requires-Dist: XlsxWriter ==3.0.8
Requires-Dist: requests >=2.20.0
Requires-Dist: rsa ==4.9
Requires-Dist: schedule ==1.1.0
Requires-Dist: PyMySQL ==1.0.2
